Workbook
Name Slicer_region_name: #N/A

Sheet Summary
D14: PERFORMANCE BY REGION
D16: Region | E16: Earned | F16: Cost | G16: Margin | H16: Margin % | I16: Status
C17: 1 | D17: =CUBERANKEDMEMBER("ThisWorkbookDataModel",Support!$J$2,C17) -> Gulf Coast | E17: =CUBEVALUE("ThisWorkbookDataModel",$D17,"[Measures].[Sum of earned_revenue_pln]") -> 3.3004125e+09 | F17: =CUBEVALUE("ThisWorkbookDataModel",$D17,"[Measures].[Sum of total_cost_pln]") -> 2.8779783e+09 | G17: =E17-F17 -> 4.2243424e+08 | H17: =G17/E17 -> 0.12799437 | I17: ●
C18: 2 | D18: =CUBERANKEDMEMBER("ThisWorkbookDataModel",Support!$J$2,C18) -> Midwest | E18: =CUBEVALUE("ThisWorkbookDataModel",$D18,"[Measures].[Sum of earned_revenue_pln]") -> 1.9588599e+09 | F18: =CUBEVALUE("ThisWorkbookDataModel",$D18,"[Measures].[Sum of total_cost_pln]") -> 1.6965395e+09 | G18: =E18-F18 -> 2.6232032e+08 | H18: =G18/E18 -> 0.1339148 | I18: ●
C19: 3 | D19: =CUBERANKEDMEMBER("ThisWorkbookDataModel",Support!$J$2,C19) -> Northeast | E19: =CUBEVALUE("ThisWorkbookDataModel",$D19,"[Measures].[Sum of earned_revenue_pln]") -> 1.6433589e+09 | F19: =CUBEVALUE("ThisWorkbookDataModel",$D19,"[Measures].[Sum of total_cost_pln]") -> 1.3985521e+09 | G19: =E19-F19 -> 2.4480677e+08 | H19: =G19/E19 -> 0.14896732 | I19: ●
C20: 4 | D20: =CUBERANKEDMEMBER("ThisWorkbookDataModel",Support!$J$2,C20) -> Other | E20: =CUBEVALUE("ThisWorkbookDataModel",$D20,"[Measures].[Sum of earned_revenue_pln]") -> 2.9205918e+09 | F20: =CUBEVALUE("ThisWorkbookDataModel",$D20,"[Measures].[Sum of total_cost_pln]") -> 2.5342107e+09 | G20: =E20-F20 -> 3.8638107e+08 | H20: =G20/E20 -> 0.13229547 | I20: ●
C21: 5 | D21: =CUBERANKEDMEMBER("ThisWorkbookDataModel",Support!$J$2,C21) -> South | E21: =CUBEVALUE("ThisWorkbookDataModel",$D21,"[Measures].[Sum of earned_revenue_pln]") -> 2.3421186e+09 | F21: =CUBEVALUE("ThisWorkbookDataModel",$D21,"[Measures].[Sum of total_cost_pln]") -> 2.148865e+09 | G21: =E21-F21 -> 1.9325368e+08 | H21: =G21/E21 -> 0.082512337 | I21: ●
C22: 6 | D22: =CUBERANKEDMEMBER("ThisWorkbookDataModel",Support!$J$2,C22) -> West | E22: =CUBEVALUE("ThisWorkbookDataModel",$D22,"[Measures].[Sum of earned_revenue_pln]") -> 1.4584291e+09 | F22: =CUBEVALUE("ThisWorkbookDataModel",$D22,"[Measures].[Sum of total_cost_pln]") -> 1.2819993e+09 | G22: =E22-F22 -> 1.7642982e+08 | H22: =G22/E22 -> 0.1209725 | I22: ●
H26: Status Legend
H27: ● | I27: On Track (≥12% growth)
H28: ● | I28: Monitor (10-12% growth)
H29: ● | I29: Action Needed (<10% growth)

Sheet Subsidiary Dashboard
B2: =B4 & " Subsidiary Dashboard" -> Gulf Coast Subsidiary Dashboard | L2: 🏠 Summary
B3: Performance Tracker
B4: =Support!E15 -> Gulf Coast
B6: Financial Summary
B7: EARNED | C7: COST | D7: MARGIN | E7: MARGIN % | F7: INVOICED | G7: UNBILLED (WIP)
B8: =GETPIVOTDATA("[Measures].[Sum of earned_revenue_pln]",Support!$B$14) -> 3.3004125e+09 | C8: =GETPIVOTDATA("[Measures].[Sum of total_cost_pln]",Support!$C$14) -> 2.8779783e+09 | D8: =B8-C8 -> 4.2243424e+08 | E8: =D8/B8 -> 0.12799437 | F8: =GETPIVOTDATA("[Measures].[Sum of invoiced_revenue_pln]",Support!$D$14) -> 3.1686235e+09 | G8: =B8-F8 -> 1.3178904e+08
B14: PROJECT | C14: EARNED | D14: COST | E14: MARGIN | F14: MARGIN % | G14: INVOICED | H14: UNBILLED (WIP)
B15: Baton Rouge Refinery | C15: 3.6225874e+08 | D15: 3.1073849e+08 | E15: 51520247 | F15: 0.14221947 | G15: 3.4735008e+08 | H15: 14908656
B16: Baytown Refinery | C16: 3.8121861e+08 | D16: 3.3816326e+08 | E16: 43055342 | F16: 0.11294134 | G16: 3.7433432e+08 | H16: 6884283.9
B17: Beaumont Petrochem Plant | C17: 7.6751112e+08 | D17: 6.679925e+08 | E17: 99518619 | F17: 0.12966407 | G17: 7.2394119e+08 | H17: 43569934
B18: Freeport Chemicals Plant | C18: 69427625 | D18: 65471849 | E18: 3955776.6 | F18: 0.056976982 | G18: 69041505 | H18: 386120.17
B19: Houston Marine Terminal | C19: 4.9807821e+08 | D19: 4.1343454e+08 | E19: 84643664 | F19: 0.16994051 | G19: 4.780362e+08 | H19: 20042010
B20: Lake Charles Refinery | C20: 1.4420282e+08 | D20: 1.2127011e+08 | E20: 22932711 | F20: 0.15903095 | G20: 1.4325635e+08 | H20: 946466.53
B21: New Orleans LPG Terminal | C21: 1.4928801e+08 | D21: 1.1963643e+08 | E21: 29651580 | F21: 0.19861997 | G21: 1.4306492e+08 | H21: 6223093.7
B22: Pascagoula Refinery | C22: 5.265547e+08 | D22: 4.7183419e+08 | E22: 54720513 | F22: 0.1039218 | G22: 5.1083213e+08 | H22: 15722572
B23: Port Arthur Refinery | C23: 2.6423409e+08 | D23: 2.5295259e+08 | E23: 11281497 | F23: 0.042695086 | G23: 2.4515418e+08 | H23: 19079914
B24: Texas City Refinery | C24: 1.3763862e+08 | D24: 1.1648433e+08 | E24: 21154287 | F24: 0.15369442 | G24: 1.3361263e+08 | H24: 4025985.8

Sheet Cash Dashboard
B2: =B4 & " Cash Dashboard" -> Gulf Coast Cash Dashboard | K2: 🏠 Summary
B3: Performance Tracker
B4: =Support!E15 -> Gulf Coast
B6: Financial Summary
B7: EARNED | C7: INVOICED | D7: CASH RECEIVED | E7: UNBILLED (WIP) | F7: AR (Receivables) | G7: CUSTOMER ADVANCES
B8: =GETPIVOTDATA("[Measures].[Sum of earned_revenue_pln]",Support!$B$14) -> 3.3004125e+09 | C8: =GETPIVOTDATA("[Measures].[Sum of invoiced_revenue_pln]",Support!$D$14) -> 3.1686235e+09 | D8: =GETPIVOTDATA("[Measures].[Sum of cash_received_pln]",Support!$F$14) -> 1.1760513e+10 | E8: =B8-C8 -> 1.3178904e+08 | F8: =GETPIVOTDATA("[Measures].[AR (Receivables)]",Support!$G$14) -> 1.0491555e+09 | G8: =GETPIVOTDATA("[Measures].[CUSTOMER ADVANCES]",Support!$H$14) -> 7.3338479e+08
B14: PROJECT | C14: INVOICED | D14: CASH IN | E14: AR Net | F14: UNBILLED (WIP) | G14: NET CASH FLOW | H14: CUSTOMER ADVANCES
B15: Beaumont Petrochem Plant | C15: 7.2394119e+08 | D15: 6.5929931e+08 | E15: 64641879 | F15: 43569934 | G15: 3.8002705e+08 | H15: 1.8828656e+08
B16: Pascagoula Refinery | C16: 5.1083213e+08 | D16: 4.3027999e+08 | E16: 80552139 | F16: 15722572 | G16: 1.5810248e+08 | H16: 1.4957273e+08
B17: Houston Marine Terminal | C17: 4.780362e+08 | D17: 4.2321907e+08 | E17: 54817129 | F17: 20042010 | G17: 2.689083e+08 | H17: 1.2259356e+08
B18: Baytown Refinery | C18: 3.7433432e+08 | D18: 3.2747043e+08 | E18: 46863896 | F18: 6884283.9 | G18: 2.0585992e+08 | H18: 78459311
B19: Baton Rouge Refinery | C19: 3.4735008e+08 | D19: 3.0235637e+08 | E19: 9643391.4 | F19: 14908656 | G19: 46882534 | H19: 21432769
B20: Port Arthur Refinery | C20: 2.4515418e+08 | D20: 2.2041504e+08 | E20: 24739135 | F20: 19079914 | G20: 1.5861718e+08 | H20: 70055081
B21: Lake Charles Refinery | C21: 1.4325635e+08 | D21: 1.2992497e+08 | E21: 2792595.5 | F21: 946466.53 | G21: 26552820 | H21: 12169792
B22: New Orleans LPG Terminal | C22: 1.4306492e+08 | D22: 1.2548552e+08 | E22: 17579398 | F22: 6223093.7 | G22: 92294253 | H22: 25448054
B23: Texas City Refinery | C23: 1.3361263e+08 | D23: 1.2637896e+08 | E23: 7233677.8 | F23: 4025985.8 | G23: 79199930 | H23: 44387025
B24: Freeport Chemicals Plant | C24: 69041505 | D24: 62133991 | E24: 6907514.3 | F24: 386120.17 | G24: 34612356 | H24: 20979910

Sheet DATA DICTIONARY
B3: KPI | C3: TYPE | D3: GOOD WHEN | E3: BUSINESS DEFINITION | F3: MODEL LOGIC | G3: NEGATIVE VALUE MEANS | H3: SOURCE | I3: NOTES
B4: EARNED | C4: AMOUNT | D4: HIGHER | E4: Recognized project revenue/earned value in the selected scope (project/month/region). | F4: Calculated from your existing Earned measure (no new base measures). | G4: Reversal/adjustment in source data. | H4: Project model measures | I4: Confirm whether it’s monthly or cumulative.
B5: COST | C5: AMOUNT | D5: LOWER | E5: Project costs in the selected scope. | F5: Calculated from your existing Cost measure. | G5: Reversal/adjustment in source data. | H5: Project model measures | I5: Cost is “good down”.
B6: MARGIN | C6: AMOUNT | D6: HIGHER | E6: Profit contribution: how much remains after costs. | F6: EARNED - COST | G6: Loss (costs exceed earned). | H6: Calculated measure | I6: Depends on slicers.
B7: MARGIN % | C7: % | D7: HIGHER | E7: Profitability ratio. | F7: MARGIN / EARNED | G7: Loss ratio / negative profitability. | H7: Calculated measure | I7: Handle division by zero.
B8: UNBILLED | C8: AMOUNT | D8: LOWER (context) | E8: Earned value not yet invoiced (potential future billing). | F8: Use your existing UNBILLED measure definition. | G8: Overbilled (invoiced > earned) / timing difference. | H8: Project model measures | I8: Your model determines exact logic.
B9: CASH IN | C9: AMOUNT | D9: HIGHER | E9: Cash received from customers in the selected scope. | F9: Use your existing Cash In measure. | G9: Refund/adjustment. | H9: Cash flow measures | I9: No “USD” suffix.
B10: CASH OUT | C10: AMOUNT | D10: LOWER | E10: Cash paid out (suppliers, costs paid) in the selected scope. | F10: Use your existing Cash Out measure. | G10: Reversal/adjustment. | H10: Cash flow measures | I10: Good down.
B11: CASH FLOW | C11: AMOUNT | D11: HIGHER | E11: Net cash movement. | F11: CASH IN - CASH OUT | G11: Net cash burn. | H11: Calculated measure | I11: Monthly vs cumulative – confirm.
B12: AR (RECEIVABLES) | C12: AMOUNT | D12: LOWER | E12: Outstanding customer receivables (invoiced minus cash received). | F12: Use your existing AR measure (based on your real column names). | G12: Prepayments / over-collection / adjustments. | H12: Project model measures | I12: Only if AR is par
B17: TABLE / OBJECT | C17: GRAIN | D17: PRIMARY KEYS | E17: MAIN FIELDS | F17: USED IN (KPIs) | G17: NOTES
B18: FACT_PROJECT_MONTH | C18: Project–Month (per company/region/client) | D18: month_key, project_id (or project_key), company_key, region_key, client_key | E18: earned_revenue_pln; invoiced_revenue_pln; cash_received_pln; total_cost_pln (or cost components); fx_rate; progress_pct | F18: EARNED; INVOICED; CASH RECEIVED; COST; UNBILLED (WIP); AR (RECEIVABLES); CUSTOMER ADVANCES; AR NET; CASH IN; CASH OUT; NET CASH FLOW | G18: Base fact table for most KPIs. USD conversion = PLN / fx_rate (if dashboards shown in USD).
B19: DIM_PROJECT | C19: 1 row per project | D19: project_id (or project_key) | E19: project_name_pretty; project_name; company_key; client_key | F19: All project-level pivots (PROJECT rows); filtering/grouping | G19: Provides “pretty” project names for reporting.
B20: DIM_REGION | C20: 1 row per region | D20: region_key | E20: region_name | F20: Region slicer + all region splits | G20: Slicer_region_name should be connected to all pivots that must react to region.
B21: DIM_DATE_MONTH | C21: 1 row per month | D21: month_key | E21: year; month_number; month_name; month_label | F21: Time filters; monthly trends (if added) | G21: Use for timeline / monthly analysis instead of raw month_key in visuals.
B22: DIM_COMPANY | C22: 1 row per company | D22: company_key | E22: company_name | F22: All company splits (if added) | G22: Optional if you ever add Company slicer.
B23: DIM_CLIENT | C23: 1 row per client | D23: client_key | E23: client_name | F23: Client reporting (if added) | G23: Optional if you ever add Client slicer.
B24: FACT_PROJECT_CONTRACT | C24: Project (contract-level) | D24: project_id (or project_key) | E24: contract_value_pln; change_orders_pln; total_contract_pln; budget_total_cost_pln; planned_margin_pct | F24: Contract / plan context (optional visuals) | G24: Useful for Planned vs Actual comparisons (later).
B25: FACT_COMMITMENTS | C25: Project–Month or Project–Vendor (depends on table) | D25: project_id, month_key (and vendor_key if applicable) | E25: committed_cost_pln (or similar) | F25: Future CASH OUT / commitments (later) | G25: Use if you expand Cash Out beyond actual cost.
B26: FACT_FORECAST_SNAPSHOT | C26: Snapshot–Project–Month | D26: snapshot_date_key; project_id; month_key | E26: forecast_revenue_pln; forecast_cost_pln (or similar) | F26: Forecast reporting (later) | G26: Snapshot logic: compare snapshots over time.
B27: FACT_BASELINE_MONTH | C27: Project–Month | D27: project_id; month_key | E27: baseline_revenue_pln; baseline_cost_pln (or similar) | F27: Baseline vs Actual (later) | G27: Only if you plan baseline tracking on dashboards.
B28: FACT_RESOURCE_PLAN_MONTH | C28: Project–Month | D28: project_id; month_key | E28: resource_cost_pln (or similar) | F28: Capacity / resource planning (later) | G28: Optional for PMO-style views.
B29: DIM_VENDOR | C29: 1 row per vendor | D29: vendor_key | E29: vendor_name | F29: Vendor analysis (later) | G29: Optional unless you build vendor dashboards.
B34: CHECK | C34: WHAT IT VALIDATES | D34: HOW TO READ IT | E34: IF IT FAILS (MOST COMMON REASONS) | F34: WHAT TO DO
B35: UNBILLED (WIP) < 0 | C35: Invoiced > Earned (timing / overbilling) | D35: Negative is possible but should be explainable | E35: Milestones billed ahead; wrong mapping; fx_rate issue | F35: Confirm billing schedule; check project/month rows; validate fx_rate
B36: AR (RECEIVABLES) < 0 | C36: Cash received > Invoiced (prepayments / overcollection) | D36: Negative AR usually means prepayment / advance payment | E36: Advance invoices; payment posted to wrong project | F36: Check CUSTOMER ADVANCES logic; verify payment allocation
B37: CASH RECEIVED > INVOICED | C37: Over-collection / advances | D37: Common in projects with deposits | E37: Payments booked early; data posting lag | F37: Confirm if advance; reconcile against invoicing timing
B38: EARNED = 0 but COST > 0 | C38: Costs incurred before revenue recognition | D38: Typical at early stage of project | E38: Missing progress_pct; earned logic; wrong month assignment | F38: Check progress_pct / earned calculation; confirm month_key mapping
B39: MARGIN % very high (>40%) or very low (<0%) | C39: Outliers in profitability | D39: Might be real but should be investigated | E39: Missing cost components; revenue posted wrong month | F39: Check cost completeness; validate revenue/cost timing
B40: NET CASH FLOW extreme swings month-to-month | C40: Volatility in cash movement | D40: Look for one-off invoices/cash spikes | E40: Lump-sum billing; late payments; data gaps | F40: Add month view; identify top projects driving the change
B41: FX_RATE = 0 or blank | C41: USD conversion invalid | D41: Any division by fx breaks measures | E41: Bad data load / missing fx | F41: Filter fx_rate blank; fix in source; add default rule (optional)
B42: PROJECT totals don’t match region totals | C42: Slicer / pivot connections issue | D42: Usually a model connection problem | E42: Slicer not connected to all pivots | F42: Report Connections: connect slicer to all pivot tables
B43: Row height changes / layout jumps | C43: Pivot formatting consistency | D43: Visual annoyance but affects usability | E43: Autofit or “Wrap text” turning on | F43: Disable “Autofit column width on update”; turn off Wrap Text; set fixed row height

Sheet Support
B1: Earned | C1: Cost | D1: Margin | E1: Margin%
B2: =CUBEVALUE("ThisWorkbookDataModel","[Measures].[Sum of earned_revenue_pln]") -> 1.3623771e+10 | C2: =CUBEVALUE("ThisWorkbookDataModel","[Measures].[Sum of total_cost_pln]") -> 1.1938145e+10 | D2: =B2-C2 -> 1.6856259e+09 | E2: =IFERROR(D2/B2,0) -> 0.12372682 | J2: =CUBESET("ThisWorkbookDataModel","[dim_region].[region_name].[region_name].MEMBERS","All Regions") -> All Regions
B4: Row Labels | C4: Sum of invoiced_revenue_pln
B5: Gulf Coast | C5: 3.1686235e+09
B6: Midwest | C6: 1.854057e+09
B7: Northeast | C7: 1.5462225e+09
B8: Other | C8: 2.8513605e+09
B9: South | C9: 2.2129061e+09
B10: West | C10: 1.4424193e+09
B11: Grand Total | C11: 1.3075589e+10
B14: Sum of earned_revenue_pln | C14: Sum of total_cost_pln | D14: Sum of invoiced_revenue_pln | E14: Row Labels | F14: Sum of cash_received_pln | G14: AR (Receivables) | H14: CUSTOMER ADVANCES | I14: AR Net
B15: 3.3004125e+09 | C15: 2.8779783e+09 | D15: 3.1686235e+09 | E15: Gulf Coast | F15: 1.1760513e+10 | G15: 1.0491555e+09 | H15: 7.3338479e+08 | I15: 1.0412661e+09
